moonshade/__init__.py
moonshade/driver/__init__.py
moonshade/driver/client.py
moonshade/proto/__init__.py
moonshade/proto/moonshade_pb2.py
moonshade/proto/moonshade_pb2_grpc.py
moonshade-0.0.2.dist-info/METADATA
moonshade-0.0.2.dist-info/RECORD
moonshade-0.0.2.dist-info/WHEEL
moonshade-0.0.2.dist-info/top_level.txt
