Metadata-Version: 2.1
Name: moonshade
Version: 0.0.2
Summary: A Universal Distributed Data Collection Framework
Home-page: https://github.com/kinaopen/moonshade
Author: Kina Wakasa
Author-email: wakasakina@gmail.com
License: UNKNOWN
Platform: UNKNOWN
Classifier: Programming Language :: Python :: 3
Classifier: License :: OSI Approved :: GNU Affero General Public License v3 or later (AGPLv3+)
Classifier: Operating System :: OS Independent
Requires-Dist: googleapis-common-protos (>=1.5.3)
Requires-Dist: grpcio (==1.13.0)
